ccxw/__init__.py
ccxw/binance.py
ccxw/binanceus.py
ccxw/bingx.py
ccxw/bybit.py
ccxw/ccxw.py
ccxw/ccxw_common_functions.py
ccxw/kucoin.py
ccxw/okx.py
ccxw/safe_thread_vars.py
ccxw-0.2.34.dist-info/METADATA
ccxw-0.2.34.dist-info/WHEEL
ccxw-0.2.34.dist-info/licenses/LICENSE
ccxw-0.2.34.dist-info/RECORD
