Metadata-Version: 2.4
Name: ccxw
Version: 0.2.34
Summary: Ccxw - CryptoCurrency eXchange Websocket Library
License: MIT
License-File: LICENSE
Author: Ricardo Marcelo Alvarez
Author-email: rmalvarezkai@gmail.com
Requires-Python: >=3.13,<4.0
Classifier: License :: OSI Approved :: MIT License
Classifier: Programming Language :: Python :: 3
Classifier: Programming Language :: Python :: 3.13
Classifier: Programming Language :: Python :: 3.14
Requires-Dist: humanize (>=4.14.0,<5.0.0)
Requires-Dist: importlib (>=1.0.4,<2.0.0)
Requires-Dist: schema (>=0.7.8,<0.8.0)
Requires-Dist: thread6 (>=0.2.0,<0.3.0)
Requires-Dist: toml (>=0.10.2,<0.11.0)
Requires-Dist: websocket-client (>=1.9.0,<2.0.0)
Requires-Dist: websocket-server (>=0.6.4,<0.7.0)
Project-URL: Homepage, https://github.com/rmalvarezkai/ccxw
